ai_kissing/__init__.py
ai_kissing-1767774.217.43.dist-info/licenses/LICENSE
ai_kissing-1767774.217.43.dist-info/METADATA
ai_kissing-1767774.217.43.dist-info/WHEEL
ai_kissing-1767774.217.43.dist-info/top_level.txt
ai_kissing-1767774.217.43.dist-info/RECORD
