Metadata-Version: 2.4
Name: ai-kissing
Version: 1767774.217.43
Summary: High-quality integration for https://supermaker.ai/video/ai-kissing/
Home-page: https://supermaker.ai/video/ai-kissing/
Author: SuperMaker
Classifier: Programming Language :: Python :: 3
Classifier: License :: OSI Approved :: MIT License
Requires-Python: >=3.6
License-File: LICENSE
Dynamic: author
Dynamic: classifier
Dynamic: description
Dynamic: description-content-type
Dynamic: home-page
Dynamic: license-file
Dynamic: requires-python
Dynamic: summary
